idh/__init__.py
idh/client.py
idh/types.py
idh-0.1.0.dist-info/METADATA
idh-0.1.0.dist-info/WHEEL
idh-0.1.0.dist-info/top_level.txt
idh-0.1.0.dist-info/RECORD
